[
    {
        "name": "Trinity College & Book of Kells",
        "coordinates": {
            "lat": 53.3438,
            "lng": -6.2546
        },
        "description": "Historic university with a famous library and medieval manuscript.",
        "extra": {
            "category": "Cultural",
            "neighborhood": "City Centre"
        },
        "travel_times": {
            "Kilmainham Gaol": {
                "public_transport": 25,
                "taxi": 15
            },
            "Guinness Storehouse": {
                "walking": 20,
                "public_transport": 15,
                "taxi": 10
            },
            "Phoenix Park": {
                "public_transport": 30,
                "taxi": 20
            },
            "Fri Location 7pm": {
                "walking": 15,
                "public_transport": 10,
                "taxi": 10
            },
            "Howth": {
                "public_transport": 40,
                "taxi": 35
            },
            "Dun Laoghaire": {
                "public_transport": 35,
                "taxi": 30
            },
            "Dalkey & Killiney": {
                "public_transport": 40,
                "taxi": 35
            },
            "Malahide": {
                "public_transport": 35,
                "taxi": 30
            },
            "Glendalough & Wicklow Mountains": {
                "tour_bus": 60,
                "taxi": 70
            },
            "DCU Appts": {
                "public_transport": 30,
                "taxi": 20
            }
        }
    },
    {
        "name": "Kilmainham Gaol",
        "coordinates": {
            "lat": 53.3419,
            "lng": -6.3096
        },
        "description": "Former prison turned museum, key to Irish independence history.",
        "extra": {
            "category": "Historical",
            "neighborhood": "Kilmainham"
        },
        "travel_times": {
            "Trinity College & Book of Kells": {
                "public_transport": 25,
                "taxi": 15
            },
            "Guinness Storehouse": {
                "walking": 18,
                "public_transport": 10,
                "taxi": 7
            },
            "Phoenix Park": {
                "public_transport": 20,
                "taxi": 12
            },
            "Fri Location 7pm": {
                "public_transport": 25,
                "taxi": 15
            },
            "Howth": {
                "public_transport": 50,
                "taxi": 40
            },
            "Dun Laoghaire": {
                "public_transport": 45,
                "taxi": 35
            },
            "Dalkey & Killiney": {
                "public_transport": 55,
                "taxi": 45
            },
            "Malahide": {
                "public_transport": 50,
                "taxi": 40
            },
            "Glendalough & Wicklow Mountains": {
                "tour_bus": 70,
                "taxi": 80
            },
            "DCU Appts": {
                "public_transport": 35,
                "taxi": 20
            }
        }
    },
    {
        "name": "Guinness Storehouse",
        "coordinates": {
            "lat": 53.3419,
            "lng": -6.2869
        },
        "description": "Iconic brewery with self-guided tours and rooftop bar.",
        "extra": {
            "category": "Attraction",
            "neighborhood": "The Liberties"
        },
        "travel_times": {
            "Trinity College & Book of Kells": {
                "walking": 20,
                "public_transport": 15,
                "taxi": 10
            },
            "Kilmainham Gaol": {
                "walking": 18,
                "public_transport": 10,
                "taxi": 7
            },
            "Phoenix Park": {
                "public_transport": 25,
                "taxi": 15
            },
            "Fri Location 7pm": {
                "public_transport": 20,
                "taxi": 12
            },
            "Howth": {
                "public_transport": 45,
                "taxi": 40
            },
            "Dun Laoghaire": {
                "public_transport": 40,
                "taxi": 35
            },
            "Dalkey & Killiney": {
                "public_transport": 50,
                "taxi": 45
            },
            "Malahide": {
                "public_transport": 45,
                "taxi": 40
            },
            "Glendalough & Wicklow Mountains": {
                "tour_bus": 70,
                "taxi": 80
            },
            "DCU Appts": {
                "public_transport": 30,
                "taxi": 20
            }
        }
    },
    {
        "name": "Phoenix Park",
        "coordinates": {
            "lat": 53.355,
            "lng": -6.3292
        },
        "description": "One of Europe's largest city parks, home to deer and Áras an Uachtaráin.",
        "extra": {
            "category": "Park",
            "neighborhood": "Dublin 8"
        },
        "travel_times": {
            "Trinity College & Book of Kells": {
                "public_transport": 30,
                "taxi": 20
            },
            "Kilmainham Gaol": {
                "public_transport": 20,
                "taxi": 12
            },
            "Guinness Storehouse": {
                "public_transport": 25,
                "taxi": 15
            },
            "Fri Location 7pm": {
                "public_transport": 30,
                "taxi": 20
            },
            "Howth": {
                "public_transport": 60,
                "taxi": 50
            },
            "Dun Laoghaire": {
                "public_transport": 55,
                "taxi": 45
            },
            "Dalkey & Killiney": {
                "public_transport": 65,
                "taxi": 55
            },
            "Malahide": {
                "public_transport": 50,
                "taxi": 40
            },
            "Glendalough & Wicklow Mountains": {
                "tour_bus": 80,
                "taxi": 90
            },
            "DCU Appts": {
                "public_transport": 40,
                "taxi": 25
            }
        }
    },
    {
        "name": "Howth",
        "coordinates": {
            "lat": 53.3881,
            "lng": -6.0639
        },
        "description": "Scenic coastal village with cliff walks and seafood.",
        "extra": {
            "category": "Day Trip",
            "neighborhood": "Howth Peninsula"
        },
        "travel_times": {
            "Trinity College & Book of Kells": {
                "public_transport": 40,
                "taxi": 35
            },
            "Kilmainham Gaol": {
                "public_transport": 50,
                "taxi": 40
            },
            "Guinness Storehouse": {
                "public_transport": 45,
                "taxi": 40
            },
            "Phoenix Park": {
                "public_transport": 60,
                "taxi": 50
            },
            "Fri Location 7pm": {
                "public_transport": 45,
                "taxi": 40
            },
            "Dun Laoghaire": {
                "public_transport": 60,
                "taxi": 50
            },
            "Dalkey & Killiney": {
                "public_transport": 70,
                "taxi": 60
            },
            "Malahide": {
                "public_transport": 30,
                "taxi": 25
            },
            "Glendalough & Wicklow Mountains": {
                "tour_bus": 90,
                "taxi": 100
            },
            "DCU Appts": {
                "public_transport": 50,
                "taxi": 40
            }
        }
    },
    {
        "name": "Dun Laoghaire",
        "coordinates": {
            "lat": 53.2932,
            "lng": -6.1373
        },
        "description": "Seaside town known for its pier walk and Teddy’s Ice Cream.",
        "extra": {
            "category": "Day Trip",
            "neighborhood": "South Dublin"
        },
        "travel_times": {
            "Trinity College & Book of Kells": {
                "public_transport": 35,
                "taxi": 30
            },
            "Kilmainham Gaol": {
                "public_transport": 45,
                "taxi": 35
            },
            "Guinness Storehouse": {
                "public_transport": 40,
                "taxi": 35
            },
            "Phoenix Park": {
                "public_transport": 55,
                "taxi": 45
            },
            "Fri Location 7pm": {
                "public_transport": 30,
                "taxi": 25
            },
            "Howth": {
                "public_transport": 60,
                "taxi": 50
            },
            "Dalkey & Killiney": {
                "public_transport": 20,
                "taxi": 15
            },
            "Malahide": {
                "public_transport": 60,
                "taxi": 50
            },
            "Glendalough & Wicklow Mountains": {
                "tour_bus": 80,
                "taxi": 90
            },
            "DCU Appts": {
                "public_transport": 50,
                "taxi": 40
            }
        }
    },
    {
        "name": "Dalkey & Killiney",
        "coordinates": {
            "lat": 53.2766,
            "lng": -6.1058
        },
        "description": "Charming village with coastal views and cliff walks.",
        "extra": {
            "category": "Day Trip",
            "neighborhood": "South Dublin"
        },
        "travel_times": {
            "Trinity College & Book of Kells": {
                "public_transport": 40,
                "taxi": 35
            },
            "Kilmainham Gaol": {
                "public_transport": 55,
                "taxi": 45
            },
            "Guinness Storehouse": {
                "public_transport": 50,
                "taxi": 45
            },
            "Phoenix Park": {
                "public_transport": 65,
                "taxi": 55
            },
            "Fri Location 7pm": {
                "public_transport": 35,
                "taxi": 30
            },
            "Howth": {
                "public_transport": 70,
                "taxi": 60
            },
            "Dun Laoghaire": {
                "public_transport": 20,
                "taxi": 15
            },
            "Malahide": {
                "public_transport": 70,
                "taxi": 60
            },
            "Glendalough & Wicklow Mountains": {
                "tour_bus": 90,
                "taxi": 100
            },
            "DCU Appts": {
                "public_transport": 60,
                "taxi": 50
            }
        }
    },
    {
        "name": "Glendalough & Wicklow Mountains",
        "coordinates": {
            "lat": 53.0102,
            "lng": -6.3277
        },
        "description": "Monastic site with lakes and scenic hiking trails.",
        "extra": {
            "category": "Nature",
            "neighborhood": "Wicklow"
        },
        "travel_times": {
            "Trinity College & Book of Kells": {
                "tour_bus": 60,
                "taxi": 70
            },
            "Kilmainham Gaol": {
                "tour_bus": 70,
                "taxi": 80
            },
            "Guinness Storehouse": {
                "tour_bus": 70,
                "taxi": 80
            },
            "Phoenix Park": {
                "tour_bus": 80,
                "taxi": 90
            },
            "Fri Location 7pm": {
                "tour_bus": 70,
                "taxi": 80
            },
            "Howth": {
                "tour_bus": 90,
                "taxi": 100
            },
            "Dun Laoghaire": {
                "tour_bus": 80,
                "taxi": 90
            },
            "Dalkey & Killiney": {
                "tour_bus": 90,
                "taxi": 100
            },
            "Malahide": {
                "tour_bus": 90,
                "taxi": 100
            },
            "DCU Appts": {
                "tour_bus": 80,
                "taxi": 90
            }
        }
    },
    {
        "name": "Malahide",
        "coordinates": {
            "lat": 53.4508,
            "lng": -6.1543
        },
        "description": "Coastal town with a castle and gardens.",
        "extra": {
            "category": "Day Trip",
            "neighborhood": "North Dublin"
        },
        "travel_times": {
            "Trinity College & Book of Kells": {
                "public_transport": 35,
                "taxi": 30
            },
            "Kilmainham Gaol": {
                "public_transport": 50,
                "taxi": 40
            },
            "Guinness Storehouse": {
                "public_transport": 45,
                "taxi": 40
            },
            "Phoenix Park": {
                "public_transport": 50,
                "taxi": 40
            },
            "Fri Location 7pm": {
                "public_transport": 40,
                "taxi": 35
            },
            "Howth": {
                "public_transport": 30,
                "taxi": 25
            },
            "Dun Laoghaire": {
                "public_transport": 60,
                "taxi": 50
            },
            "Dalkey & Killiney": {
                "public_transport": 70,
                "taxi": 60
            },
            "Glendalough & Wicklow Mountains": {
                "tour_bus": 90,
                "taxi": 100
            },
            "DCU Appts": {
                "public_transport": 40,
                "taxi": 30
            }
        }
    },
    {
        "name": "DCU Appts",
        "coordinates": {
            "lat": 53.3861,
            "lng": -6.2568
        },
        "description": "Dublin City University accommodation with twin rooms and common areas.",
        "extra": {
            "category": "Accommodation",
            "neighborhood": "Glasnevin"
        },
        "travel_times": {
            "Trinity College & Book of Kells": {
                "public_transport": 30,
                "taxi": 20
            },
            "Kilmainham Gaol": {
                "public_transport": 35,
                "taxi": 20
            },
            "Guinness Storehouse": {
                "public_transport": 30,
                "taxi": 20
            },
            "Phoenix Park": {
                "public_transport": 40,
                "taxi": 25
            },
            "Fri Location 7pm": {
                "public_transport": 35,
                "taxi": 20
            },
            "Howth": {
                "public_transport": 50,
                "taxi": 40
            },
            "Dun Laoghaire": {
                "public_transport": 50,
                "taxi": 40
            },
            "Dalkey & Killiney": {
                "public_transport": 60,
                "taxi": 50
            },
            "Malahide": {
                "public_transport": 40,
                "taxi": 30
            },
            "Glendalough & Wicklow Mountains": {
                "tour_bus": 80,
                "taxi": 90
            }
        }
    },
    {
        "name": "Fri Location 7pm",
        "coordinates": {
            "lat": 53.3338,
            "lng": -6.2654
        },
        "description": "Ryan's Bar, casual pub on Camden Street, popular Friday night spot.",
        "extra": {
            "category": "Bar",
            "neighborhood": "Camden Street"
        },
        "travel_times": {
            "Trinity College & Book of Kells": {
                "walking": 15,
                "public_transport": 10,
                "taxi": 10
            },
            "Kilmainham Gaol": {
                "public_transport": 25,
                "taxi": 15
            },
            "Guinness Storehouse": {
                "public_transport": 20,
                "taxi": 12
            },
            "Phoenix Park": {
                "public_transport": 30,
                "taxi": 20
            },
            "Howth": {
                "public_transport": 45,
                "taxi": 40
            },
            "Dun Laoghaire": {
                "public_transport": 30,
                "taxi": 25
            },
            "Dalkey & Killiney": {
                "public_transport": 35,
                "taxi": 30
            },
            "Malahide": {
                "public_transport": 40,
                "taxi": 35
            },
            "Glendalough & Wicklow Mountains": {
                "tour_bus": 70,
                "taxi": 80
            },
            "DCU Appts": {
                "public_transport": 35,
                "taxi": 20
            }
        }
    }
]